SJARACNe/Makefile
SJARACNe/__init__.py
SJARACNe/sjaracne.py
SJARACNe/bin/QC_input.py
SJARACNe/bin/__init__.py
SJARACNe/bin/ch_line_ending.py
SJARACNe/bin/create_consensus_network.py
SJARACNe/config/config_kernel.txt
SJARACNe/config/config_threshold.txt
SJARACNe/cwl/QC_input.cwl
SJARACNe/cwl/ch_line_ending.cwl
SJARACNe/cwl/copy_files_to_dir.cwl
SJARACNe/cwl/create_consensus_network.cwl
SJARACNe/cwl/get_consensus_network.cwl
SJARACNe/cwl/get_enhanced_consensus_network.cwl
SJARACNe/cwl/int_to_int_array.cwl
SJARACNe/cwl/int_to_str_array.cwl
SJARACNe/cwl/sjaracne.cwl
SJARACNe/cwl/sjaracne_workflow.cwl
SJARACNe/src/main.cpp
SJARACNe/src/matrix.cpp
SJARACNe/src/matrix.h
SJARACNe/src/param.cpp
SJARACNe/src/param.h
SJARACNe/src/parseargs.h
SJARACNe/src/util.cpp
SJARACNe/src/util.h
SJARACNe-0.2.0.dist-info/LICENSE.md
SJARACNe-0.2.0.dist-info/METADATA
SJARACNe-0.2.0.dist-info/WHEEL
SJARACNe-0.2.0.dist-info/entry_points.txt
SJARACNe-0.2.0.dist-info/top_level.txt
SJARACNe-0.2.0.dist-info/RECORD
